engscript/__init__.py
engscript/__main__.py
engscript/assemble.py
engscript/colors.py
engscript/doc.py
engscript/engscript.py
engscript/export.py
engscript/importer.py
engscript/math.py
engscript/utils.py
engscript-0.0.2.dist-info/METADATA
engscript-0.0.2.dist-info/WHEEL
engscript-0.0.2.dist-info/entry_points.txt
engscript-0.0.2.dist-info/licenses/LICENSE
engscript-0.0.2.dist-info/RECORD
