Metadata-Version: 2.4
Name: engscript
Version: 0.0.2
Summary: EngScript is an experimental library aiming to provide fast OpenSCAD-like, python tool, with integrated rendering and assembly capabilities
Project-URL: Homepage, https://gitbuilding.gitlab.io/engscript/
Project-URL: Bug Tracker, https://gitlab.com/gitbuilding/engscript/issues
Project-URL: Source Code, https://gitlab.com/gitbuilding/engscript
Author-email: Julian Stirling <julian@julianstirling.co.uk>
License-File: LICENSE
Keywords: CAD,Mesh,hardware
Classifier: License :: OSI Approved :: MIT License
Requires-Python: >=3.10
Requires-Dist: cascadio
Requires-Dist: ezdxf
Requires-Dist: manifold3d
Requires-Dist: matplotlib
Requires-Dist: numpy>=2
Requires-Dist: pdoc
Requires-Dist: pillow
Requires-Dist: pyglet<2
Requires-Dist: pyyaml
Requires-Dist: scipy
Requires-Dist: trimesh
Provides-Extra: dev
Requires-Dist: autopep8; extra == 'dev'
Requires-Dist: colorama; extra == 'dev'
Requires-Dist: coverage; extra == 'dev'
Requires-Dist: mkdocs; extra == 'dev'
Requires-Dist: mypy~=1.11; extra == 'dev'
Requires-Dist: pylint; extra == 'dev'
Requires-Dist: pylint-mccabe; extra == 'dev'
Requires-Dist: pytest; extra == 'dev'
Requires-Dist: types-pyyaml; extra == 'dev'
